{
  "json://0.5616216063499451": {
    "steps": [
      0
    ],
    "timestamps": [
      "2020-04-16T09:47:53.830580"
    ],
    "values": [
      "loss.train"
    ]
  },
  "json://0.5774760383386581": {
    "steps": [
      0
    ],
    "timestamps": [
      "2020-04-16T09:47:53.830574"
    ],
    "values": [
      "acc.test"
    ]
  },
  "json://0.6": {
    "steps": [
      0
    ],
    "timestamps": [
      "2020-04-16T09:47:53.830568"
    ],
    "values": [
      "acc.train"
    ]
  },
  "json://0.7931309904153354": {
    "steps": [
      0
    ],
    "timestamps": [
      "2020-04-16T09:47:53.830587"
    ],
    "values": [
      "acc.test.best"
    ]
  },
  "json://2.548365354537964": {
    "steps": [
      0
    ],
    "timestamps": [
      "2020-04-16T09:47:53.830532"
    ],
    "values": [
      "training_time"
    ]
  }
}