{
  "json://0.00019246335432399064": {
    "steps": [
      0
    ],
    "timestamps": [
      "2020-04-16T09:36:01.194600"
    ],
    "values": [
      "loss.train"
    ]
  },
  "json://1.0": {
    "steps": [
      0,
      1,
      2
    ],
    "timestamps": [
      "2020-04-16T09:36:01.194587",
      "2020-04-16T09:36:01.194593",
      "2020-04-16T09:36:01.194610"
    ],
    "values": [
      "acc.train",
      "acc.test",
      "acc.test.best"
    ]
  },
  "json://2.380851984024048": {
    "steps": [
      0
    ],
    "timestamps": [
      "2020-04-16T09:36:01.194548"
    ],
    "values": [
      "training_time"
    ]
  }
}