{
  "acc.test": {
    "steps": [
      0
    ],
    "timestamps": [
      "2020-04-16T10:56:24.257116"
    ],
    "values": [
      0.5391373801916933
    ]
  },
  "acc.test.best": {
    "steps": [
      0
    ],
    "timestamps": [
      "2020-04-16T10:56:24.257126"
    ],
    "values": [
      0.8138977635782748
    ]
  },
  "acc.train": {
    "steps": [
      0
    ],
    "timestamps": [
      "2020-04-16T10:56:24.257109"
    ],
    "values": [
      0.5
    ]
  },
  "json://2.342569351196289": {
    "steps": [
      0
    ],
    "timestamps": [
      "2020-04-16T10:56:24.257070"
    ],
    "values": [
      "training_time"
    ]
  },
  "loss.train": {
    "steps": [
      0
    ],
    "timestamps": [
      "2020-04-16T10:56:24.257120"
    ],
    "values": [
      NaN
    ]
  }
}