{
  "acc.test": {
    "steps": [
      0
    ],
    "timestamps": [
      "2020-04-16T11:33:21.792116"
    ],
    "values": [
      0.6156405990016639
    ]
  },
  "acc.test.best": {
    "steps": [
      0
    ],
    "timestamps": [
      "2020-04-16T11:33:21.792126"
    ],
    "values": [
      0.6206322795341098
    ]
  },
  "acc.train": {
    "steps": [
      0
    ],
    "timestamps": [
      "2020-04-16T11:33:21.792110"
    ],
    "values": [
      1.0
    ]
  },
  "json://2.5029938220977783": {
    "steps": [
      0
    ],
    "timestamps": [
      "2020-04-16T11:33:21.792076"
    ],
    "values": [
      "training_time"
    ]
  },
  "loss.train": {
    "steps": [
      0
    ],
    "timestamps": [
      "2020-04-16T11:33:21.792120"
    ],
    "values": [
      0.0001017330214381218
    ]
  }
}