{
  "acc.test": {
    "steps": [
      0
    ],
    "timestamps": [
      "2020-04-16T10:48:43.430187"
    ],
    "values": [
      0.9642857142857143
    ]
  },
  "acc.test.best": {
    "steps": [
      0
    ],
    "timestamps": [
      "2020-04-16T10:48:43.430197"
    ],
    "values": [
      1.0
    ]
  },
  "acc.train": {
    "steps": [
      0
    ],
    "timestamps": [
      "2020-04-16T10:48:43.430181"
    ],
    "values": [
      1.0
    ]
  },
  "json://2.422342538833618": {
    "steps": [
      0
    ],
    "timestamps": [
      "2020-04-16T10:48:43.430140"
    ],
    "values": [
      "training_time"
    ]
  },
  "loss.train": {
    "steps": [
      0
    ],
    "timestamps": [
      "2020-04-16T10:48:43.430191"
    ],
    "values": [
      0.00022030336549505591
    ]
  }
}