{
  "json://0.0009372786735184491": {
    "steps": [
      0
    ],
    "timestamps": [
      "2020-04-16T09:44:07.841783"
    ],
    "values": [
      "loss.train"
    ]
  },
  "json://0.5973377703826955": {
    "steps": [
      0
    ],
    "timestamps": [
      "2020-04-16T09:44:07.841778"
    ],
    "values": [
      "acc.test"
    ]
  },
  "json://0.6356073211314476": {
    "steps": [
      0
    ],
    "timestamps": [
      "2020-04-16T09:44:07.841789"
    ],
    "values": [
      "acc.test.best"
    ]
  },
  "json://1.0": {
    "steps": [
      0
    ],
    "timestamps": [
      "2020-04-16T09:44:07.841773"
    ],
    "values": [
      "acc.train"
    ]
  },
  "json://2.4713246822357178": {
    "steps": [
      0
    ],
    "timestamps": [
      "2020-04-16T09:44:07.841743"
    ],
    "values": [
      "training_time"
    ]
  }
}