{
  "acc.test": {
    "steps": [
      0
    ],
    "timestamps": [
      "2020-04-16T11:12:52.862947"
    ],
    "values": [
      0.6945412311265969
    ]
  },
  "acc.test.best": {
    "steps": [
      0
    ],
    "timestamps": [
      "2020-04-16T11:12:52.862957"
    ],
    "values": [
      0.9175377468060395
    ]
  },
  "acc.train": {
    "steps": [
      0
    ],
    "timestamps": [
      "2020-04-16T11:12:52.862941"
    ],
    "values": [
      0.782608695652174
    ]
  },
  "json://2.3639512062072754": {
    "steps": [
      0
    ],
    "timestamps": [
      "2020-04-16T11:12:52.862907"
    ],
    "values": [
      "training_time"
    ]
  },
  "loss.train": {
    "steps": [
      0
    ],
    "timestamps": [
      "2020-04-16T11:12:52.862951"
    ],
    "values": [
      0.4059563875198364
    ]
  }
}